[{"timestamp": "2025-01-15 08:00:00", "asset": "BTC", "price": 97166.25, "size": 0.0343107081661544, "pnl": 0.5095140162675307, "pnl_pct": 0.0152854204880314, "reason": "Mean reversion target reached for BTC (price $97,166.25 >= SMA $96,714.88)"}, {"timestamp": "2025-01-18 03:00:00", "asset": "ETH", "price": 3383.41, "size": 1.0049788946470322, "pnl": 67.32353615240481, "pnl_pct": 2.0199492223542226, "reason": "Trailing stop-loss triggered for ETH (price $3,383.41 < stop $3,408.22, HWM=$3,516.09, ATR stop=3.1%)"}, {"timestamp": "2025-01-18 10:00:00", "asset": "ETH", "price": 3264.9, "size": 1.0070227853267777, "pnl": -119.34227028907615, "pnl_pct": -3.5026792496327563, "reason": "Trailing stop-loss triggered for ETH (price $3,264.90 < stop $3,266.56, HWM=$3,383.41, ATR stop=3.5%)"}, {"timestamp": "2025-01-19 08:00:00", "asset": "ETH", "price": 3216.83, "size": 1.0299042568251435, "pnl": -49.507497625585074, "pnl_pct": -1.472326870654539, "reason": "Trailing stop-loss triggered for ETH (price $3,216.83 < stop $3,249.50, HWM=$3,350.00, ATR stop=3.0%)"}, {"timestamp": "2025-01-19 23:00:00", "asset": "BTC", "price": 101211.13, "size": 0.0336779371011578, "pnl": 75.07889873835347, "pnl_pct": 2.2522522067438544, "reason": "Trailing stop-loss triggered for BTC (price $101,211.13 < stop $102,658.29, HWM=$106,165.23, ATR stop=3.3%)"}, {"timestamp": "2025-01-20 21:00:00", "asset": "BTC", "price": 102479.85, "size": 0.0328490294858294, "pnl": 41.67622068926176, "pnl_pct": 1.25353802491881, "reason": "Trailing stop-loss triggered for BTC (price $102,479.85 < stop $102,722.84, HWM=$108,178.16, ATR stop=5.0%)"}, {"timestamp": "2025-01-22 16:00:00", "asset": "BTC", "price": 103700.19, "size": 0.0325779113379577, "pnl": 39.75612832216348, "pnl_pct": 1.1908097055177258, "reason": "Trailing stop-loss triggered for BTC (price $103,700.19 < stop $103,840.26, HWM=$107,051.81, ATR stop=3.0%)"}, {"timestamp": "2025-01-25 00:00:00", "asset": "ETH", "price": 3273.32, "size": 0.9924428621484692, "pnl": -125.5737953476455, "pnl_pct": -3.721634778004901, "reason": "Trailing stop-loss triggered for ETH (price $3,273.32 < stop $3,297.85, HWM=$3,399.85, ATR stop=3.0%)"}, {"timestamp": "2025-01-25 23:00:00", "asset": "BTC", "price": 104733.56, "size": 0.0323223275675894, "pnl": 33.400923638519544, "pnl_pct": 0.9964976920485924, "reason": "Mean reversion target reached for BTC (price $104,733.56 >= SMA $104,689.95)"}, {"timestamp": "2025-01-25 23:00:00", "asset": "ETH", "price": 3318.37, "size": 1.0135299623953649, "pnl": 45.65952480591068, "pnl_pct": 1.3762785184461055, "reason": "Mean reversion target reached for ETH (price $3,318.37 >= SMA $3,315.71)"}, {"timestamp": "2025-01-26 23:00:00", "asset": "ETH", "price": 3231.48, "size": 1.0026346815785514, "pnl": -96.33314020606711, "pnl_pct": -2.8874009784947474, "reason": "Trailing stop-loss triggered for ETH (price $3,231.48 < stop $3,250.93, HWM=$3,351.47, ATR stop=3.0%)"}, {"timestamp": "2025-01-27 00:00:00", "asset": "BTC", "price": 101677.81, "size": 0.0318760641490056, "pnl": -95.2386669431162, "pnl_pct": -2.8545962431396954, "reason": "Mean reversion time exit for BTC (10291 candles elapsed)"}, {"timestamp": "2025-01-27 01:00:00", "asset": "BTC", "price": 101221.82, "size": 0.0321846998079895, "pnl": -14.675901265444736, "pnl_pct": -0.4484655993279074, "reason": "Mean reversion time exit for BTC (10290 candles elapsed)"}, {"timestamp": "2025-01-27 01:00:00", "asset": "ETH", "price": 3193.66, "size": 1.0184900972853903, "pnl": -19.75870788733664, "pnl_pct": -0.6037857992069906, "reason": "Mean reversion time exit for ETH (10290 candles elapsed)"}, {"timestamp": "2025-01-27 02:00:00", "asset": "BTC", "price": 100930.27, "size": 0.0322162908050148, "pnl": -9.392659584202192, "pnl_pct": -0.2880307822957562, "reason": "Mean reversion time exit for BTC (10289 candles elapsed)"}, {"timestamp": "2025-01-27 02:00:00", "asset": "ETH", "price": 3168.58, "size": 1.0210828920213393, "pnl": -25.60875893189541, "pnl_pct": -0.7853058872891894, "reason": "Mean reversion time exit for ETH (10289 candles elapsed)"}, {"timestamp": "2025-01-27 03:00:00", "asset": "BTC", "price": 101364.7, "size": 0.0321937556436488, "pnl": 13.985933264270445, "pnl_pct": 0.430425877192242, "reason": "Mean reversion time exit for BTC (10288 candles elapsed)"}, {"timestamp": "2025-01-27 03:00:00", "asset": "ETH", "price": 3182.49, "size": 1.025482850181313, "pnl": 14.264466446021745, "pnl_pct": 0.4389979107360275, "reason": "Mean reversion time exit for ETH (10288 candles elapsed)"}, {"timestamp": "2025-01-27 09:00:00", "asset": "BTC", "price": 99380.38, "size": 0.0162348193100532, "pnl": -15.948112401037632, "pnl_pct": -0.9787897338772722, "reason": "Trend-exit (50%) triggered for BTC"}, {"timestamp": "2025-01-30 09:00:00", "asset": "BTC", "price": 105400.47, "size": 0.0162348193100532, "pnl": 81.78696097922057, "pnl_pct": 5.019543113219727, "reason": "Mean reversion target reached for BTC (price $105,400.47 >= SMA $103,997.74)"}, {"timestamp": "2025-01-31 18:00:00", "asset": "BTC", "price": 102565.23, "size": 0.0310717746058933, "pnl": -93.80382322871584, "pnl_pct": -2.85927331720276, "reason": "Trailing stop-loss triggered for BTC (price $102,565.23 < stop $102,572.61, HWM=$105,744.96, ATR stop=3.0%)"}, {"timestamp": "2025-01-31 18:00:00", "asset": "ETH", "price": 3313.67, "size": 0.9565878144770962, "pnl": -109.7684517112466, "pnl_pct": -3.347022826841517, "reason": "Trailing stop-loss triggered for ETH (price $3,313.67 < stop $3,318.65, HWM=$3,428.42, ATR stop=3.2%)"}, {"timestamp": "2025-01-31 21:00:00", "asset": "ETH", "price": 3317.55, "size": 0.9695685168439652, "pnl": 3.7619258453546536, "pnl_pct": 0.1170907181463398, "reason": "Mean reversion target reached for ETH (price $3,317.55 >= SMA $3,304.97)"}, {"timestamp": "2025-01-31 21:00:00", "asset": "BTC", "price": 102111.73, "size": 0.0313247492079951, "pnl": -14.205773765825596, "pnl_pct": -0.4421576395821414, "reason": "Mean reversion time exit for BTC (10174 candles elapsed)"}, {"timestamp": "2025-02-01 04:00:00", "asset": "ETH", "price": 3294.02, "size": 0.9689945847786212, "pnl": -17.461282417710663, "pnl_pct": -0.5440755546430642, "reason": "Mean reversion time exit for ETH (10167 candles elapsed)"}, {"timestamp": "2025-02-01 04:00:00", "asset": "BTC", "price": 102297.43, "size": 0.0312935561058138, "pnl": -8.098459384623766, "pnl_pct": -0.2523396435633152, "reason": "Mean reversion time exit for BTC (10167 candles elapsed)"}, {"timestamp": "2025-02-21 15:00:00", "asset": "ETH", "price": 2723.72, "size": 1.169073205439192, "pnl": -16.60083951723709, "pnl_pct": -0.5186418887330624, "reason": "Trailing stop-loss triggered for ETH (price $2,723.72 < stop $2,744.17, HWM=$2,837.21, ATR stop=3.3%)"}, {"timestamp": "2025-02-21 19:00:00", "asset": "BTC", "price": 95232.71, "size": 0.0325491054663077, "pnl": -101.37386348376047, "pnl_pct": -3.166831389200697, "reason": "Trailing stop-loss triggered for BTC (price $95,232.71 < stop $96,387.70, HWM=$99,368.76, ATR stop=3.0%)"}, {"timestamp": "2025-02-22 09:00:00", "asset": "ETH", "price": 2714.18, "size": 1.1722602899897463, "pnl": -11.183363166502204, "pnl_pct": -0.3502562671640286, "reason": "Mean reversion target reached for ETH (price $2,714.18 >= SMA $2,684.88)"}, {"timestamp": "2025-02-22 09:00:00", "asset": "BTC", "price": 96484.92, "size": 0.0328517332747616, "pnl": 41.13726892398927, "pnl_pct": 1.3148948507293312, "reason": "Mean reversion target reached for BTC (price $96,484.92 >= SMA $96,470.99)"}, {"timestamp": "2025-02-23 14:00:00", "asset": "BTC", "price": 95595.59, "size": 0.0164978948001624, "pnl": -8.618335264656935, "pnl_pct": -0.5434883254933132, "reason": "Trend-exit (50%) triggered for BTC"}, {"timestamp": "2025-02-24 22:00:00", "asset": "BTC", "price": 92427.84, "size": 0.0164978948001624, "pnl": -60.8795415178713, "pnl_pct": -3.839177643974623, "reason": "Trailing stop-loss triggered for BTC (price $92,427.84 < stop $93,378.00, HWM=$96,265.98, ATR stop=3.0%)"}, {"timestamp": "2025-03-03 14:00:00", "asset": "BTC", "price": 89188.42, "size": 0.0342971054375464, "pnl": -89.41804141255352, "pnl_pct": -2.8401803224076816, "reason": "Trailing stop-loss triggered for BTC (price $89,188.42 < stop $90,410.56, HWM=$93,562.64, ATR stop=3.4%)"}, {"timestamp": "2025-03-03 19:00:00", "asset": "BTC", "price": 85510.54, "size": 0.0349654884810891, "pnl": -128.59887077482836, "pnl_pct": -4.12371920031771, "reason": "Trailing stop-loss triggered for BTC (price $85,510.54 < stop $85,797.80, HWM=$90,235.37, ATR stop=4.9%)"}, {"timestamp": "2025-03-04 00:00:00", "asset": "BTC", "price": 85971.7, "size": 0.035968085126094, "pnl": 16.58704213674946, "pnl_pct": 0.5393019386849884, "reason": "Mean reversion time exit for BTC (9427 candles elapsed)"}, {"timestamp": "2025-03-06 17:00:00", "asset": "BTC", "price": 88597.9, "size": 0.0335229563496229, "pnl": -111.1158615755876, "pnl_pct": -3.606276925058749, "reason": "Trailing stop-loss triggered for BTC (price $88,597.90 < stop $89,107.62, HWM=$91,912.52, ATR stop=3.1%)"}, {"timestamp": "2025-03-07 00:00:00", "asset": "BTC", "price": 85515.27, "size": 0.0343590624091389, "pnl": -105.91627655428374, "pnl_pct": -3.4793488333244804, "reason": "Trailing stop-loss triggered for BTC (price $85,515.27 < stop $86,040.50, HWM=$90,304.75, ATR stop=4.7%)"}, {"timestamp": "2025-03-07 16:00:00", "asset": "BTC", "price": 87163.36, "size": 0.035184772847008, "pnl": 57.98767228142515, "pnl_pct": 1.9272464438222503, "reason": "Trailing stop-loss triggered for BTC (price $87,163.36 < stop $87,284.94, HWM=$90,445.82, ATR stop=3.5%)"}, {"timestamp": "2025-03-08 02:00:00", "asset": "BTC", "price": 86148.02, "size": 0.0173706278302853, "pnl": -17.637093261201926, "pnl_pct": -1.164870193163725, "reason": "Trend-exit (50%) triggered for BTC"}, {"timestamp": "2025-03-08 09:00:00", "asset": "BTC", "price": 85905.16, "size": 0.0173706278302853, "pnl": -21.855723936065036, "pnl_pct": -1.4434964416240923, "reason": "Trailing stop-loss triggered for BTC (price $85,905.16 < stop $85,905.84, HWM=$88,562.72, ATR stop=3.0%)"}, {"timestamp": "2025-03-16 19:00:00", "asset": "BTC", "price": 83102.88, "size": 0.0365022174531343, "pnl": 18.43909514645111, "pnl_pct": 0.6115785506454197, "reason": "Mean reversion time exit for BTC (9120 candles elapsed)"}, {"timestamp": "2025-03-20 10:00:00", "asset": "ETH", "price": 1981.91, "size": 1.4802141412843068, "pnl": -87.49545789131525, "pnl_pct": -2.896100969123272, "reason": "Trailing stop-loss triggered for ETH (price $1,981.91 < stop $1,995.35, HWM=$2,057.06, ATR stop=3.0%)"}, {"timestamp": "2025-03-21 12:00:00", "asset": "BTC", "price": 83430.4, "size": 0.0350724538402448, "pnl": -91.29780604061853, "pnl_pct": -3.02570439986648, "reason": "Trailing stop-loss triggered for BTC (price $83,430.40 < stop $83,661.83, HWM=$86,249.31, ATR stop=3.0%)"}, {"timestamp": "2025-03-22 21:00:00", "asset": "ETH", "price": 1985.91, "size": 1.5043859862495264, "pnl": 6.017543944998124, "pnl_pct": 0.2018255117538059, "reason": "Mean reversion time exit for ETH (8974 candles elapsed)"}, {"timestamp": "2025-03-22 21:00:00", "asset": "BTC", "price": 84003.05, "size": 0.0352766528359966, "pnl": 20.20117524653415, "pnl_pct": 0.6863805039889703, "reason": "Mean reversion time exit for BTC (8974 candles elapsed)"}, {"timestamp": "2025-03-26 13:00:00", "asset": "ETH", "price": 2028.8, "size": 1.481987608924971, "pnl": 36.36797592301855, "pnl_pct": 1.224392044944267, "reason": "Trailing stop-loss triggered for ETH (price $2,028.80 < stop $2,034.69, HWM=$2,097.62, ATR stop=3.0%)"}, {"timestamp": "2025-03-28 04:00:00", "asset": "ETH", "price": 1937.44, "size": 1.48070205022643, "pnl": -135.27693930868645, "pnl_pct": -4.503154574132484, "reason": "Trailing stop-loss triggered for ETH (price $1,937.44 < stop $1,970.80, HWM=$2,031.75, ATR stop=3.0%)"}, {"timestamp": "2025-03-28 06:00:00", "asset": "BTC", "price": 85699.54, "size": 0.0348731719727707, "pnl": 23.89858475293977, "pnl_pct": 0.8061002486171587, "reason": "Trailing stop-loss triggered for BTC (price $85,699.54 < stop $85,832.16, HWM=$88,486.76, ATR stop=3.0%)"}, {"timestamp": "2025-03-28 14:00:00", "asset": "BTC", "price": 84124.23, "size": 0.0343675709988609, "pnl": -54.13957827021568, "pnl_pct": -1.8381778945371183, "reason": "Mean reversion time exit for BTC (8837 candles elapsed)"}, {"timestamp": "2025-04-06 18:00:00", "asset": "ETH", "price": 1617.29, "size": 1.738234176012095, "pnl": -116.0097489070472, "pnl_pct": -3.963112296099236, "reason": "Trailing stop-loss triggered for ETH (price $1,617.29 < stop $1,617.47, HWM=$1,684.03, ATR stop=4.0%)"}, {"timestamp": "2025-04-06 18:00:00", "asset": "BTC", "price": 79037.09, "size": 0.0181191990136187, "pnl": -31.53048654752888, "pnl_pct": -2.1542820343250058, "reason": "Trend-exit (50%) triggered for BTC"}, {"timestamp": "2025-04-06 22:00:00", "asset": "BTC", "price": 77984.1, "size": 0.0181191990136187, "pnl": -50.60982191687913, "pnl_pct": -3.457854351583589, "reason": "Trailing stop-loss triggered for BTC (price $77,984.10 < stop $78,353.94, HWM=$80,777.26, ATR stop=3.0%)"}, {"timestamp": "2025-04-16 00:00:00", "asset": "BTC", "price": 83135.44, "size": 0.034212150388019, "pnl": -16.946304451697415, "pnl_pct": -0.5922820033822496, "reason": "Trailing stop-loss triggered for BTC (price $83,135.44 < stop $83,396.45, HWM=$85,975.72, ATR stop=3.0%)"}, {"timestamp": "2025-04-20 20:00:00", "asset": "BTC", "price": 85122.97, "size": 0.034348043531799, "pnl": 68.26776696075649, "pnl_pct": 2.3907132746275206, "reason": "Mean reversion target reached for BTC (price $85,122.97 >= SMA $84,721.14)"}, {"timestamp": "2025-04-21 17:00:00", "asset": "ETH", "price": 1578.62, "size": 1.7697232767109872, "pnl": -84.57507539401831, "pnl_pct": -2.938373472863553, "reason": "Trailing stop-loss triggered for ETH (price $1,578.62 < stop $1,585.46, HWM=$1,634.50, ATR stop=3.0%)"}, {"timestamp": "2025-04-22 01:00:00", "asset": "ETH", "price": 1587.58, "size": 0.9023245672920334, "pnl": 8.084828122936642, "pnl_pct": 0.5675843458210261, "reason": "Trend-exit (50%) triggered for ETH"}, {"timestamp": "2025-04-23 04:00:00", "asset": "ETH", "price": 1817.46, "size": 0.2255811418230083, "pnl": 53.87779991300732, "pnl_pct": 15.129670218291944, "reason": "Take-profit level 1 triggered for ETH (price $1,817.46 >= $1,815.41, selling 25%)"}, {"timestamp": "2025-04-24 07:00:00", "asset": "ETH", "price": 1756.79, "size": 0.676743425469025, "pnl": 120.57537611581644, "pnl_pct": 11.286440055238137, "reason": "Trailing stop-loss triggered for ETH (price $1,756.79 < stop $1,762.94, HWM=$1,817.46, ATR stop=3.0% [breakeven])"}, {"timestamp": "2025-04-28 00:00:00", "asset": "ETH", "price": 1774.42, "size": 1.6898612142828595, "pnl": 29.79225320780688, "pnl_pct": 1.0035348561865831, "reason": "Trailing stop-loss triggered for ETH (price $1,774.42 < stop $1,787.60, HWM=$1,842.89, ATR stop=3.0%)"}, {"timestamp": "2025-04-28 16:00:00", "asset": "ETH", "price": 1758.54, "size": 1.686375647042512, "pnl": -26.779645275035364, "pnl_pct": -0.8949403185266269, "reason": "Trailing stop-loss triggered for ETH (price $1,758.54 < stop $1,762.59, HWM=$1,817.10, ATR stop=3.0%)"}, {"timestamp": "2025-04-30 12:00:00", "asset": "ETH", "price": 1775.88, "size": 1.6984692278381994, "pnl": 29.4514564107144, "pnl_pct": 0.986045242075817, "reason": "Trailing stop-loss triggered for ETH (price $1,775.88 < stop $1,778.44, HWM=$1,833.44, ATR stop=3.0%)"}, {"timestamp": "2025-05-04 23:00:00", "asset": "BTC", "price": 94272.55, "size": 0.0330905178096823, "pnl": 241.23186026365283, "pnl_pct": 8.381066120319147, "reason": "Trailing stop-loss triggered for BTC (price $94,272.55 < stop $94,859.87, HWM=$97,793.68, ATR stop=3.0%)"}, {"timestamp": "2025-05-05 01:00:00", "asset": "ETH", "price": 1791.74, "size": 1.692480519336645, "pnl": 26.842741036678945, "pnl_pct": 0.8930783611505122, "reason": "Trailing stop-loss triggered for ETH (price $1,791.74 < stop $1,804.74, HWM=$1,860.56, ATR stop=3.0%)"}, {"timestamp": "2025-05-05 03:00:00", "asset": "BTC", "price": 94047.17, "size": 0.0320439714833634, "pnl": -7.222070292920762, "pnl_pct": -0.2390727735698261, "reason": "Mean reversion time exit for BTC (7936 candles elapsed)"}, {"timestamp": "2025-05-05 03:00:00", "asset": "ETH", "price": 1794.56, "size": 1.6785176982086916, "pnl": 4.733419908948235, "pnl_pct": 0.1573889068726464, "reason": "Mean reversion time exit for ETH (7936 candles elapsed)"}, {"timestamp": "2025-05-07 02:00:00", "asset": "BTC", "price": 96628.52, "size": 0.0321035036378715, "pnl": 91.81409419409464, "pnl_pct": 3.04999819769054, "reason": "Mean reversion target reached for BTC (price $96,628.52 >= SMA $94,977.08)"}, {"timestamp": "2025-05-08 19:00:00", "asset": "ETH", "price": 2118.29, "size": 0.4151417875184677, "pnl": 119.29514406130691, "pnl_pct": 15.694756216786, "reason": "Take-profit level 1 triggered for ETH (price $2,118.29 >= $2,105.57, selling 25%)"}, {"timestamp": "2025-05-10 22:00:00", "asset": "ETH", "price": 2579.43, "size": 0.435898876894391, "pnl": 326.2703093554516, "pnl_pct": 40.880863823302896, "reason": "Take-profit level 2 triggered for ETH (price $2,579.43 >= $2,563.30, selling 35%)"}, {"timestamp": "2025-05-11 13:00:00", "asset": "ETH", "price": 2469.52, "size": 0.809526485661012, "pnl": 516.9555184782655, "pnl_pct": 34.87790357905545, "reason": "Trailing stop-loss triggered for ETH (price $2,469.52 < stop $2,472.36, HWM=$2,583.80, ATR stop=4.3% [breakeven])"}, {"timestamp": "2025-05-12 18:00:00", "asset": "BTC", "price": 101630.99, "size": 0.0313398397115607, "pnl": 144.1942891144945, "pnl_pct": 4.741822116871086, "reason": "Trailing stop-loss triggered for BTC (price $101,630.99 < stop $101,676.55, HWM=$104,821.19, ATR stop=3.0%)"}, {"timestamp": "2025-05-12 18:00:00", "asset": "ETH", "price": 2435.37, "size": 1.3907310518858913, "pnl": -47.49346542190324, "pnl_pct": -1.3828598270109185, "reason": "Trailing stop-loss triggered for ETH (price $2,435.37 < stop $2,448.78, HWM=$2,577.55, ATR stop=5.0%)"}, {"timestamp": "2025-05-14 10:00:00", "asset": "ETH", "price": 2596.18, "size": 1.3936192771838705, "pnl": 224.107915963938, "pnl_pct": 6.603103429868962, "reason": "Trailing stop-loss triggered for ETH (price $2,596.18 < stop $2,606.69, HWM=$2,696.44, ATR stop=3.3%)"}, {"timestamp": "2025-05-15 07:00:00", "asset": "ETH", "price": 2531.28, "size": 1.3450171948244625, "pnl": -87.29161594410698, "pnl_pct": -2.499826668412808, "reason": "Trailing stop-loss triggered for ETH (price $2,531.28 < stop $2,549.30, HWM=$2,632.90, ATR stop=3.2%)"}, {"timestamp": "2025-05-16 22:00:00", "asset": "ETH", "price": 2546.84, "size": 1.359608526716487, "pnl": 21.15550867570846, "pnl_pct": 0.6147087639455151, "reason": "Trailing stop-loss triggered for ETH (price $2,546.84 < stop $2,546.90, HWM=$2,625.67, ATR stop=3.0%)"}, {"timestamp": "2025-05-17 03:00:00", "asset": "BTC", "price": 103529.59, "size": 0.0333951148077499, "pnl": 63.40396497399388, "pnl_pct": 1.868130970681281, "reason": "Mean reversion time exit for BTC (7648 candles elapsed)"}, {"timestamp": "2025-05-17 03:00:00", "asset": "ETH", "price": 2497.78, "size": 1.3617070210243614, "pnl": -66.80534645145508, "pnl_pct": -1.9263086805610063, "reason": "Mean reversion time exit for ETH (7648 candles elapsed)"}, {"timestamp": "2025-05-19 04:00:00", "asset": "BTC", "price": 103022.91, "size": 0.0328523357735992, "pnl": -60.95882312134381, "pnl_pct": -1.7692290456237658, "reason": "Trailing stop-loss triggered for BTC (price $103,022.91 < stop $103,279.26, HWM=$106,473.46, ATR stop=3.0%)"}, {"timestamp": "2025-05-19 05:00:00", "asset": "ETH", "price": 2379.2, "size": 1.3827472950319215, "pnl": -155.6696904746941, "pnl_pct": -4.51805536604356, "reason": "Mean reversion time exit for ETH (7598 candles elapsed)"}, {"timestamp": "2025-05-19 05:00:00", "asset": "BTC", "price": 103051.85, "size": 0.0326858192933284, "pnl": 0.9459276103489174, "pnl_pct": 0.028090839212358, "reason": "Mean reversion time exit for BTC (7598 candles elapsed)"}, {"timestamp": "2025-05-19 09:00:00", "asset": "BTC", "price": 103091.87, "size": 0.0329990158761526, "pnl": 28.32239534618429, "pnl_pct": 0.8395283780995966, "reason": "Mean reversion time exit for BTC (7594 candles elapsed)"}, {"timestamp": "2025-05-19 09:00:00", "asset": "ETH", "price": 2406.13, "size": 1.407830231503595, "pnl": 2.5622510213365786, "pnl_pct": 0.0756973934309623, "reason": "Mean reversion time exit for ETH (7594 candles elapsed)"}, {"timestamp": "2025-05-20 12:00:00", "asset": "ETH", "price": 2485.48, "size": 1.350922043738232, "pnl": -26.626673482080605, "pnl_pct": -0.7867666723881284, "reason": "Trailing stop-loss triggered for ETH (price $2,485.48 < stop $2,490.68, HWM=$2,571.62, ATR stop=3.1%)"}, {"timestamp": "2025-05-21 17:00:00", "asset": "ETH", "price": 2473.75, "size": 1.354704285596204, "pnl": -15.890681270043842, "pnl_pct": -0.4719410335227048, "reason": "Trailing stop-loss triggered for ETH (price $2,473.75 < stop $2,482.25, HWM=$2,599.05, ATR stop=4.5%)"}, {"timestamp": "2025-05-23 11:00:00", "asset": "ETH", "price": 2566.41, "size": 1.3669184093642175, "pnl": 126.65865981168828, "pnl_pct": 3.7457301667508816, "reason": "Trailing stop-loss triggered for ETH (price $2,566.41 < stop $2,616.92, HWM=$2,722.15, ATR stop=3.9%)"}, {"timestamp": "2025-05-23 20:00:00", "asset": "BTC", "price": 108261.23, "size": 0.0320578515109315, "pnl": 86.71969412222052, "pnl_pct": 2.5627123692389957, "reason": "Trailing stop-loss triggered for BTC (price $108,261.23 < stop $108,451.81, HWM=$111,805.99, ATR stop=3.0%)"}, {"timestamp": "2025-05-25 00:00:00", "asset": "ETH", "price": 2488.09, "size": 1.3442409540005296, "pnl": -105.28095151732076, "pnl_pct": -3.0517337448030424, "reason": "Trailing stop-loss triggered for ETH (price $2,488.09 < stop $2,505.72, HWM=$2,583.22, ATR stop=3.0%)"}, {"timestamp": "2025-05-28 19:00:00", "asset": "BTC", "price": 106956.19, "size": 0.0316896975883347, "pnl": -41.35632294068, "pnl_pct": -1.205454621197255, "reason": "Trailing stop-loss triggered for BTC (price $106,956.19 < stop $106,987.18, HWM=$110,296.06, ATR stop=3.0%)"}, {"timestamp": "2025-05-28 22:00:00", "asset": "ETH", "price": 2649.31, "size": 1.3655489052960144, "pnl": 220.15379451182295, "pnl_pct": 6.47966914380107, "reason": "Mean reversion target reached for ETH (price $2,649.31 >= SMA $2,642.31)"}, {"timestamp": "2025-05-28 22:00:00", "asset": "BTC", "price": 107431.34, "size": 0.0322678536963222, "pnl": 15.33207068380716, "pnl_pct": 0.4442473128483781, "reason": "Mean reversion time exit for BTC (7365 candles elapsed)"}, {"timestamp": "2025-05-29 14:00:00", "asset": "BTC", "price": 107642.47, "size": 0.0322399855981677, "pnl": -0.0809223638511866, "pnl_pct": -0.0023317390183907, "reason": "Mean reversion time exit for BTC (7349 candles elapsed)"}, {"timestamp": "2025-05-29 17:00:00", "asset": "BTC", "price": 106302.25, "size": 0.0325104496038803, "pnl": -14.511689389683852, "pnl_pct": -0.4181506046635475, "reason": "Mean reversion time exit for BTC (7346 candles elapsed)"}, {"timestamp": "2025-05-29 23:00:00", "asset": "BTC", "price": 105572.58, "size": 0.0163007292931109, "pnl": -11.894153143304038, "pnl_pct": -0.6864106827465966, "reason": "Trend-exit (50%) triggered for BTC"}, {"timestamp": "2025-05-31 02:00:00", "asset": "BTC", "price": 103229.54, "size": 0.0163007292931109, "pnl": -50.08741390623504, "pnl_pct": -2.8905408869520643, "reason": "Trailing stop-loss triggered for BTC (price $103,229.54 < stop $103,262.67, HWM=$106,456.36, ATR stop=3.0%)"}, {"timestamp": "2025-06-11 22:00:00", "asset": "ETH", "price": 2759.4, "size": 1.3015157407677174, "pnl": 110.40758028932532, "pnl_pct": 3.1717248006221554, "reason": "Trailing stop-loss triggered for ETH (price $2,759.40 < stop $2,769.67, HWM=$2,868.60, ATR stop=3.4%)"}, {"timestamp": "2025-06-12 11:00:00", "asset": "BTC", "price": 106932.65, "size": 0.0325544208405061, "pnl": 36.18261104318026, "pnl_pct": 1.0503093898009075, "reason": "Trailing stop-loss triggered for BTC (price $106,932.65 < stop $106,992.12, HWM=$110,301.15, ATR stop=3.0%)"}, {"timestamp": "2025-06-12 20:00:00", "asset": "ETH", "price": 2641.05, "size": 1.2722339289171751, "pnl": -150.56888548734787, "pnl_pct": -4.2889758643183225, "reason": "Trailing stop-loss triggered for ETH (price $2,641.05 < stop $2,679.17, HWM=$2,776.71, ATR stop=3.5%)"}, {"timestamp": "2025-06-13 00:00:00", "asset": "BTC", "price": 103859.25, "size": 0.032557918773039, "pnl": -100.06350755705807, "pnl_pct": -2.8741455486233525, "reason": "Trailing stop-loss triggered for BTC (price $103,859.25 < stop $105,078.65, HWM=$108,328.51, ATR stop=3.0%)"}, {"timestamp": "2025-06-13 01:00:00", "asset": "ETH", "price": 2500.42, "size": 1.3001671759399882, "pnl": -182.84250995244065, "pnl_pct": -5.324776130705599, "reason": "Trailing stop-loss triggered for ETH (price $2,500.42 < stop $2,515.72, HWM=$2,643.80, ATR stop=4.8%)"}, {"timestamp": "2025-06-13 05:00:00", "asset": "BTC", "price": 104080.2, "size": 0.0323804610738915, "pnl": 7.154462874276305, "pnl_pct": 0.2127398378093392, "reason": "Mean reversion time exit for BTC (6998 candles elapsed)"}, {"timestamp": "2025-06-13 05:00:00", "asset": "ETH", "price": 2508.62, "size": 1.3395246192781185, "pnl": 10.98410187808031, "pnl_pct": 0.3279449052559169, "reason": "Mean reversion time exit for ETH (6998 candles elapsed)"}, {"timestamp": "2025-06-17 12:00:00", "asset": "BTC", "price": 105540.7, "size": 0.0312526884830118, "pnl": -56.93521029769681, "pnl_pct": -1.696840618514095, "reason": "Mean reversion time exit for BTC (6895 candles elapsed)"}, {"timestamp": "2025-06-17 16:00:00", "asset": "ETH", "price": 2462.06, "size": 0.6674910823951943, "pnl": -24.79061880015729, "pnl_pct": -1.4860755441741258, "reason": "Trend-exit (50%) triggered for ETH"}, {"timestamp": "2025-06-17 20:00:00", "asset": "BTC", "price": 104388.35, "size": 0.0160023478236127, "pnl": 2.264972310954363, "pnl_pct": 0.1357739387900736, "reason": "Trend-exit (50%) triggered for BTC"}, {"timestamp": "2025-06-20 17:00:00", "asset": "ETH", "price": 2419.92, "size": 0.6674910823951943, "pnl": -52.91869301229076, "pnl_pct": -3.1722151088348194, "reason": "Trailing stop-loss triggered for ETH (price $2,419.92 < stop $2,477.44, HWM=$2,554.06, ATR stop=3.0%)"}, {"timestamp": "2025-06-21 18:00:00", "asset": "BTC", "price": 102684.2, "size": 0.0160023478236127, "pnl": -25.00542873265545, "pnl_pct": -1.4989523420428918, "reason": "Trailing stop-loss triggered for BTC (price $102,684.20 < stop $102,821.65, HWM=$106,001.70, ATR stop=3.0%)"}, {"timestamp": "2025-06-30 14:00:00", "asset": "ETH", "price": 2439.1, "size": 1.3447969966847546, "pnl": -34.50749093493141, "pnl_pct": -1.0410749931027865, "reason": "Trailing stop-loss triggered for ETH (price $2,439.10 < stop $2,443.98, HWM=$2,519.57, ATR stop=3.0%)"}, {"timestamp": "2025-07-01 12:00:00", "asset": "ETH", "price": 2438.73, "size": 1.3518963079057005, "pnl": -0.5002016339249167, "pnl_pct": -0.0151695297445741, "reason": "Trailing stop-loss triggered for ETH (price $2,438.73 < stop $2,440.98, HWM=$2,516.47, ATR stop=3.0%)"}, {"timestamp": "2025-07-01 19:00:00", "asset": "BTC", "price": 105403.99, "size": 0.0310843839886975, "pnl": -26.486071065249234, "pnl_pct": -0.8019024985492562, "reason": "Trailing stop-loss triggered for BTC (price $105,403.99 < stop $105,493.85, HWM=$108,756.55, ATR stop=3.0%)"}, {"timestamp": "2025-07-02 01:00:00", "asset": "ETH", "price": 2411.63, "size": 1.3504460248097931, "pnl": -36.59708727234511, "pnl_pct": -1.1112341259590042, "reason": "Mean reversion time exit for ETH (6546 candles elapsed)"}, {"timestamp": "2025-07-02 01:00:00", "asset": "BTC", "price": 105742.06, "size": 0.0309889877051142, "pnl": 10.476447073467623, "pnl_pct": 0.3207373838504557, "reason": "Mean reversion time exit for BTC (6546 candles elapsed)"}, {"timestamp": "2025-07-04 07:00:00", "asset": "ETH", "price": 2535.85, "size": 1.2756716739683305, "pnl": -33.67773219276387, "pnl_pct": -1.03034442384623, "reason": "Trailing stop-loss triggered for ETH (price $2,535.85 < stop $2,547.50, HWM=$2,626.29, ATR stop=3.0%)"}, {"timestamp": "2025-07-06 10:00:00", "asset": "BTC", "price": 108024.23, "size": 0.0299790088187811, "pnl": -35.24002507638943, "pnl_pct": -1.076458804106828, "reason": "Mean reversion time exit for BTC (6441 candles elapsed)"}, {"timestamp": "2025-07-06 10:00:00", "asset": "ETH", "price": 2509.28, "size": 1.2847681861606612, "pnl": -34.13629070628804, "pnl_pct": -1.047774907821819, "reason": "Mean reversion time exit for ETH (6441 candles elapsed)"}, {"timestamp": "2025-07-07 17:00:00", "asset": "ETH", "price": 2533.48, "size": 1.2659192148014493, "pnl": -32.16700724810471, "pnl_pct": -0.9930086873605304, "reason": "Mean reversion time exit for ETH (6410 candles elapsed)"}, {"timestamp": "2025-07-07 17:00:00", "asset": "BTC", "price": 107950.98, "size": 0.0297339016304, "pnl": -29.544199337998634, "pnl_pct": -0.9120415330360676, "reason": "Mean reversion time exit for BTC (6410 candles elapsed)"}, {"timestamp": "2025-07-08 00:00:00", "asset": "BTC", "price": 108298.89, "size": 0.0297508622233601, "pnl": 3.2077379649222166, "pnl_pct": 0.0996570234493399, "reason": "Mean reversion time exit for BTC (6403 candles elapsed)"}, {"timestamp": "2025-07-08 00:00:00", "asset": "ETH", "price": 2540.6, "size": 1.2670457244065507, "pnl": 0.2787500593690311, "pnl_pct": 0.0086601217140769, "reason": "Mean reversion time exit for ETH (6403 candles elapsed)"}, {"timestamp": "2025-07-11 05:00:00", "asset": "ETH", "price": 3006.1, "size": 0.3083111300525361, "pnl": 121.82914304025962, "pnl_pct": 15.134338076179166, "reason": "Take-profit level 1 triggered for ETH (price $3,006.10 >= $3,002.59, selling 25%)"}, {"timestamp": "2025-07-12 15:00:00", "asset": "ETH", "price": 2917.04, "size": 0.9249333901576084, "pnl": 283.1128613933429, "pnl_pct": 11.723319098412466, "reason": "Trailing stop-loss triggered for ETH (price $2,917.04 < stop $2,925.73, HWM=$3,016.22, ATR stop=3.0% [breakeven])"}, {"timestamp": "2025-07-15 01:00:00", "asset": "BTC", "price": 118506.3, "size": 0.0296001032165956, "pnl": 287.8589317741676, "pnl_pct": 8.939885570479579, "reason": "Trailing stop-loss triggered for BTC (price $118,506.30 < stop $119,069.34, HWM=$122,751.90, ATR stop=3.0%)"}, {"timestamp": "2025-07-15 02:00:00", "asset": "ETH", "price": 2975.11, "size": 1.1784320234191583, "pnl": 68.43154759995105, "pnl_pct": 1.990716616844468, "reason": "Trailing stop-loss triggered for ETH (price $2,975.11 < stop $2,975.34, HWM=$3,067.36, ATR stop=3.0%)"}, {"timestamp": "2025-07-17 06:00:00", "asset": "ETH", "price": 3442.91, "size": 0.2916867844497132, "pnl": 136.45107776557586, "pnl_pct": 15.72378836412771, "reason": "Take-profit level 1 triggered for ETH (price $3,442.91 >= $3,421.38, selling 25%)"}, {"timestamp": "2025-07-18 20:00:00", "asset": "ETH", "price": 3519.54, "size": 0.8750603533491397, "pnl": 476.409108173872, "pnl_pct": 18.29949144737504, "reason": "Trailing stop-loss triggered for ETH (price $3,519.54 < stop $3,531.71, HWM=$3,673.48, ATR stop=3.9% [breakeven])"}, {"timestamp": "2025-07-19 09:00:00", "asset": "BTC", "price": 118326.25, "size": 0.0293205500138376, "pnl": -5.279165029991418, "pnl_pct": -0.1519328508273409, "reason": "Mean reversion target reached for BTC (price $118,326.25 >= SMA $117,971.61)"}, {"timestamp": "2025-07-19 09:00:00", "asset": "ETH", "price": 3560.34, "size": 1.042143055505586, "pnl": 42.5194366646283, "pnl_pct": 1.159242400995586, "reason": "Mean reversion time exit for ETH (6130 candles elapsed)"}, {"timestamp": "2025-07-22 21:00:00", "asset": "BTC", "price": 119446.69, "size": 0.0316003887713721, "pnl": 84.17774761695682, "pnl_pct": 2.281002342209959, "reason": "Mean reversion target reached for BTC (price $119,446.69 >= SMA $118,564.15)"}, {"timestamp": "2025-07-23 16:00:00", "asset": "ETH", "price": 3572.65, "size": 1.006573441064346, "pnl": -122.30873882372862, "pnl_pct": -3.28924572839292, "reason": "Trailing stop-loss triggered for ETH (price $3,572.65 < stop $3,583.34, HWM=$3,694.16, ATR stop=3.0%)"}, {"timestamp": "2025-07-23 19:00:00", "asset": "BTC", "price": 118458.67, "size": 0.0313879593416731, "pnl": -0.2674254135913543, "pnl_pct": -0.0071918646842306, "reason": "Mean reversion time exit for BTC (6024 candles elapsed)"}, {"timestamp": "2025-07-23 19:00:00", "asset": "ETH", "price": 3590.9, "size": 1.027378513021718, "pnl": 18.749657862646472, "pnl_pct": 0.5108252977481742, "reason": "Mean reversion time exit for ETH (6024 candles elapsed)"}, {"timestamp": "2025-07-23 22:00:00", "asset": "BTC", "price": 118632.15, "size": 0.0312313999509129, "pnl": 21.21361610265785, "pnl_pct": 0.5758569245981171, "reason": "Mean reversion target reached for BTC (price $118,632.15 >= SMA $118,348.34)"}, {"timestamp": "2025-07-23 22:00:00", "asset": "ETH", "price": 3612.58, "size": 1.032282558736557, "pnl": 45.36881845647167, "pnl_pct": 1.2315650543766044, "reason": "Mean reversion time exit for ETH (6021 candles elapsed)"}, {"timestamp": "2025-07-24 03:00:00", "asset": "BTC", "price": 118557.79, "size": 0.0311164920115538, "pnl": -16.926126994605056, "pnl_pct": -0.4567187299934772, "reason": "Mean reversion target reached for BTC (price $118,557.79 >= SMA $118,415.90)"}, {"timestamp": "2025-07-24 03:00:00", "asset": "ETH", "price": 3643.21, "size": 1.0158512834924298, "pnl": -5.069097904627142, "pnl_pct": -0.1367797818102034, "reason": "Mean reversion target reached for ETH (price $3,643.21 >= SMA $3,627.53)"}, {"timestamp": "2025-07-25 03:00:00", "asset": "BTC", "price": 115400.0, "size": 0.0317731698632345, "pnl": -32.073108586743274, "pnl_pct": -0.8671461695889948, "reason": "Mean reversion time exit for BTC (5992 candles elapsed)"}, {"timestamp": "2025-07-25 04:00:00", "asset": "BTC", "price": 116127.65, "size": 0.0319584564524126, "pnl": 23.25457083759784, "pnl_pct": 0.6305459272097025, "reason": "Mean reversion time exit for BTC (5991 candles elapsed)"}, {"timestamp": "2025-07-28 14:00:00", "asset": "ETH", "price": 3785.41, "size": 0.956647114396454, "pnl": -74.45584491347608, "pnl_pct": -2.014630206769441, "reason": "Trailing stop-loss triggered for ETH (price $3,785.41 < stop $3,812.46, HWM=$3,930.37, ATR stop=3.0%)"}, {"timestamp": "2025-07-28 20:00:00", "asset": "BTC", "price": 118033.9, "size": 0.0309893036970918, "pnl": -37.96902456878797, "pnl_pct": -1.027367883699981, "reason": "Mean reversion time exit for BTC (5903 candles elapsed)"}, {"timestamp": "2025-07-28 20:00:00", "asset": "ETH", "price": 3788.34, "size": 0.9662744275006944, "pnl": 2.831184072576889, "pnl_pct": 0.0774024478193968, "reason": "Mean reversion time exit for ETH (5903 candles elapsed)"}, {"timestamp": "2025-07-29 09:00:00", "asset": "BTC", "price": 118786.52, "size": 0.0307980984107266, "pnl": -0.8272369233118297, "pnl_pct": -0.0226068814808577, "reason": "Mean reversion target reached for BTC (price $118,786.52 >= SMA $118,252.75)"}, {"timestamp": "2025-07-29 09:00:00", "asset": "ETH", "price": 3872.31, "size": 0.9610851974058504, "pnl": 62.39365101558769, "pnl_pct": 1.7051050719784522, "reason": "Mean reversion target reached for ETH (price $3,872.31 >= SMA $3,802.98)"}, {"timestamp": "2025-07-31 20:00:00", "asset": "ETH", "price": 3733.54, "size": 0.9848484374583336, "pnl": -2.7772725936329152, "pnl_pct": -0.0754745260092781, "reason": "Mean reversion time exit for ETH (5831 candles elapsed)"}, {"timestamp": "2025-07-31 21:00:00", "asset": "BTC", "price": 116517.59, "size": 0.0315825604883763, "pnl": 1.1012838842293604, "pnl_pct": 0.0299357707306269, "reason": "Mean reversion time exit for BTC (5830 candles elapsed)"}, {"timestamp": "2025-07-31 22:00:00", "asset": "BTC", "price": 116005.24, "size": 0.0315762593860608, "pnl": -16.17809649644778, "pnl_pct": -0.4397190158155428, "reason": "Mean reversion time exit for BTC (5829 candles elapsed)"}, {"timestamp": "2025-07-31 23:00:00", "asset": "BTC", "price": 115761.13, "size": 0.0316692327523009, "pnl": -7.730776407164285, "pnl_pct": -0.2104301495346239, "reason": "Mean reversion time exit for BTC (5828 candles elapsed)"}, {"timestamp": "2025-08-01 00:00:00", "asset": "BTC", "price": 115426.24, "size": 0.0158568770906844, "pnl": -5.310309568899129, "pnl_pct": -0.289293997043738, "reason": "Trend-exit (50%) triggered for BTC"}, {"timestamp": "2025-08-02 18:00:00", "asset": "BTC", "price": 112307.19, "size": 0.0158568770906844, "pnl": -54.76870205859859, "pnl_pct": -2.983678545639634, "reason": "Trailing stop-loss triggered for BTC (price $112,307.19 < stop $112,490.58, HWM=$115,969.67, ATR stop=3.0%)"}, {"timestamp": "2025-08-10 11:00:00", "asset": "ETH", "price": 4180.38, "size": 0.9359395256128568, "pnl": 261.3891907131588, "pnl_pct": 7.159006434082693, "reason": "Trailing stop-loss triggered for ETH (price $4,180.38 < stop $4,183.03, HWM=$4,312.40, ATR stop=3.0%)"}, {"timestamp": "2025-08-11 11:00:00", "asset": "ETH", "price": 4184.64, "size": 0.8968097493176835, "pnl": 3.820409532093436, "pnl_pct": 0.1019046115424915, "reason": "Trailing stop-loss triggered for ETH (price $4,184.64 < stop $4,190.05, HWM=$4,319.64, ATR stop=3.0%)"}, {"timestamp": "2025-08-12 09:00:00", "asset": "BTC", "price": 118413.72, "size": 0.0311253787817188, "pnl": 34.47820458408569, "pnl_pct": 0.9442995243210016, "reason": "Trailing stop-loss triggered for BTC (price $118,413.72 < stop $118,623.36, HWM=$122,292.12, ATR stop=3.0%)"}, {"timestamp": "2025-08-14 12:00:00", "asset": "ETH", "price": 4570.11, "size": 0.9016293910307336, "pnl": 347.55108136061654, "pnl_pct": 9.211545079146566, "reason": "Trailing stop-loss triggered for ETH (price $4,570.11 < stop $4,616.07, HWM=$4,776.63, ATR stop=3.4%)"}, {"timestamp": "2025-08-14 12:00:00", "asset": "BTC", "price": 118921.99, "size": 0.0319403934370567, "pnl": 16.23434377225294, "pnl_pct": 0.429232355845266, "reason": "Trailing stop-loss triggered for BTC (price $118,921.99 < stop $120,189.10, HWM=$123,906.29, ATR stop=3.0%)"}, {"timestamp": "2025-08-15 14:00:00", "asset": "ETH", "price": 4495.52, "size": 0.8473212738181468, "pnl": -63.20169381409505, "pnl_pct": -1.6321270166363422, "reason": "Trailing stop-loss triggered for ETH (price $4,495.52 < stop $4,533.48, HWM=$4,673.69, ATR stop=3.0%)"}, {"timestamp": "2025-08-15 19:00:00", "asset": "BTC", "price": 116997.52, "size": 0.0325621142623752, "pnl": -62.66481203451349, "pnl_pct": -1.6182625265520725, "reason": "Mean reversion time exit for BTC (5472 candles elapsed)"}, {"timestamp": "2025-08-15 19:00:00", "asset": "ETH", "price": 4384.71, "size": 0.8531476507671484, "pnl": -94.53729118150795, "pnl_pct": -2.464898387728232, "reason": "Mean reversion time exit for ETH (5472 candles elapsed)"}, {"timestamp": "2025-09-04 21:00:00", "asset": "BTC", "price": 110490.13, "size": 0.0339111361225794, "pnl": -52.03765571418171, "pnl_pct": -1.3698144676359658, "reason": "Mean reversion target reached for BTC (price $110,490.13 >= SMA $110,448.45)"}, {"timestamp": "2025-09-14 13:00:00", "asset": "ETH", "price": 4615.0, "size": 0.8593348803681338, "pnl": 159.5441138891474, "pnl_pct": 4.1915951360699255, "reason": "Trailing stop-loss triggered for ETH (price $4,615.00 < stop $4,615.69, HWM=$4,758.44, ATR stop=3.0%)"}, {"timestamp": "2025-09-15 08:00:00", "asset": "ETH", "price": 4512.02, "size": 0.8385049086363932, "pnl": -86.34923549137557, "pnl_pct": -2.2314192849404058, "reason": "Trailing stop-loss triggered for ETH (price $4,512.02 < stop $4,524.13, HWM=$4,664.05, ATR stop=3.0%)"}, {"timestamp": "2025-09-19 15:00:00", "asset": "ETH", "price": 4476.79, "size": 0.8496806309179078, "pnl": -29.934248627238503, "pnl_pct": -0.7808032765812323, "reason": "Trailing stop-loss triggered for ETH (price $4,476.79 < stop $4,485.14, HWM=$4,623.86, ATR stop=3.0%)"}, {"timestamp": "2025-09-20 05:00:00", "asset": "BTC", "price": 115775.62, "size": 0.0336784889984929, "pnl": 117.61033535608703, "pnl_pct": 3.110119414727741, "reason": "Mean reversion time exit for BTC (4622 candles elapsed)"}, {"timestamp": "2025-09-20 05:00:00", "asset": "ETH", "price": 4480.69, "size": 0.8570788311926502, "pnl": 3.3426074416511256, "pnl_pct": 0.0871159915921904, "reason": "Mean reversion time exit for ETH (4622 candles elapsed)"}, {"timestamp": "2025-09-21 02:00:00", "asset": "BTC", "price": 115752.65, "size": 0.0331973039652645, "pnl": 6.400440204502502, "pnl_pct": 0.1668399534959563, "reason": "Mean reversion time exit for BTC (4601 candles elapsed)"}, {"timestamp": "2025-10-07 14:00:00", "asset": "ETH", "price": 4596.52, "size": 0.8988398935622351, "pnl": 266.3352488614264, "pnl_pct": 6.890593715190674, "reason": "Trailing stop-loss triggered for ETH (price $4,596.52 < stop $4,607.50, HWM=$4,750.00, ATR stop=3.0%)"}, {"timestamp": "2025-10-07 15:00:00", "asset": "BTC", "price": 121914.66, "size": 0.0335439784941034, "pnl": 251.09378645739707, "pnl_pct": 6.541611119194735, "reason": "Trailing stop-loss triggered for BTC (price $121,914.66 < stop $122,316.24, HWM=$126,099.22, ATR stop=3.0%)"}, {"timestamp": "2025-10-07 23:00:00", "asset": "ETH", "price": 4449.8, "size": 0.8748159097687488, "pnl": -128.3529902812711, "pnl_pct": -3.1919800196670622, "reason": "Trailing stop-loss triggered for ETH (price $4,449.80 < stop $4,449.82, HWM=$4,596.52, ATR stop=3.2%)"}, {"timestamp": "2025-10-09 08:00:00", "asset": "ETH", "price": 4329.5, "size": 0.8904725343463978, "pnl": -107.12384588187206, "pnl_pct": -2.703492291788401, "reason": "Trailing stop-loss triggered for ETH (price $4,329.50 < stop $4,404.21, HWM=$4,540.42, ATR stop=3.0%)"}, {"timestamp": "2025-10-09 16:00:00", "asset": "BTC", "price": 119905.93, "size": 0.0327031075442688, "pnl": -65.69171321739941, "pnl_pct": -1.6476525464616087, "reason": "Trailing stop-loss triggered for BTC (price $119,905.93 < stop $120,366.90, HWM=$124,089.59, ATR stop=3.0%)"}, {"timestamp": "2025-10-09 19:00:00", "asset": "ETH", "price": 4340.51, "size": 0.4533479831283319, "pnl": 4.991361294243234, "pnl_pct": 0.2543018824344711, "reason": "Trend-exit (50%) triggered for ETH"}, {"timestamp": "2025-10-10 04:00:00", "asset": "ETH", "price": 4346.24, "size": 0.4533479831283319, "pnl": 7.589045237568371, "pnl_pct": 0.3866497286060699, "reason": "Mean reversion time exit for ETH (4143 candles elapsed)"}, {"timestamp": "2025-10-10 04:00:00", "asset": "BTC", "price": 121285.29, "size": 0.0324872539590485, "pnl": 44.81161862095314, "pnl_pct": 1.150368459675022, "reason": "Mean reversion time exit for BTC (4143 candles elapsed)"}, {"timestamp": "2025-10-10 16:00:00", "asset": "ETH", "price": 4109.53, "size": 0.4786681832505703, "pnl": 2.2880339159376035, "pnl_pct": 0.1164504537426003, "reason": "Trend-exit (50%) triggered for ETH"}, {"timestamp": "2025-10-10 20:00:00", "asset": "ETH", "price": 3871.6, "size": 0.4786681832505703, "pnl": -111.60148692487064, "pnl_pct": -5.680004872403921, "reason": "Trailing stop-loss triggered for ETH (price $3,871.60 < stop $3,933.23, HWM=$4,109.53, ATR stop=4.3%)"}, {"timestamp": "2025-10-10 20:00:00", "asset": "BTC", "price": 114317.33, "size": 0.0330042958409673, "pnl": -156.6634713260696, "pnl_pct": -3.9867268124251343, "reason": "Trailing stop-loss triggered for BTC (price $114,317.33 < stop $115,492.17, HWM=$119,064.09, ATR stop=3.0%)"}, {"timestamp": "2025-10-28 03:00:00", "asset": "ETH", "price": 4094.15, "size": 0.9328523589908364, "pnl": -67.45455407862755, "pnl_pct": -1.7355260820936746, "reason": "Trailing stop-loss triggered for ETH (price $4,094.15 < stop $4,095.11, HWM=$4,221.76, ATR stop=3.0%)"}, {"timestamp": "2025-10-28 20:00:00", "asset": "ETH", "price": 3979.88, "size": 0.9406923320821116, "pnl": -107.49291278702276, "pnl_pct": -2.7910555304519917, "reason": "Trailing stop-loss triggered for ETH (price $3,979.88 < stop $4,033.84, HWM=$4,158.60, ATR stop=3.0%)"}, {"timestamp": "2025-10-29 00:00:00", "asset": "BTC", "price": 112446.0, "size": 0.0345839280131128, "pnl": 47.85689374526555, "pnl_pct": 1.245959359173554, "reason": "Trailing stop-loss triggered for BTC (price $112,446.00 < stop $112,577.68, HWM=$116,059.46, ATR stop=3.0%)"}, {"timestamp": "2025-10-29 19:00:00", "asset": "ETH", "price": 3905.44, "size": 0.9555290259205068, "pnl": -71.12958068952275, "pnl_pct": -1.8704081530096397, "reason": "Trailing stop-loss triggered for ETH (price $3,905.44 < stop $3,906.77, HWM=$4,027.60, ATR stop=3.0%)"}, {"timestamp": "2025-10-29 23:00:00", "asset": "BTC", "price": 110032.13, "size": 0.0337626621366052, "pnl": -81.49867725168724, "pnl_pct": -2.146692634686864, "reason": "Trailing stop-loss triggered for BTC (price $110,032.13 < stop $110,173.26, HWM=$113,580.68, ATR stop=3.0%)"}, {"timestamp": "2025-10-30 01:00:00", "asset": "ETH", "price": 3928.2, "size": 0.9613814254217076, "pnl": 21.881041242597803, "pnl_pct": 0.5827768446064807, "reason": "Mean reversion time exit for ETH (3666 candles elapsed)"}, {"timestamp": "2025-10-30 01:00:00", "asset": "BTC", "price": 110453.18, "size": 0.0340566932065587, "pnl": 14.339570674620973, "pnl_pct": 0.382660955486358, "reason": "Mean reversion time exit for BTC (3666 candles elapsed)"}, {"timestamp": "2025-10-30 05:00:00", "asset": "BTC", "price": 110270.05, "size": 0.0346295802578225, "pnl": 58.804143940005815, "pnl_pct": 1.5640226076788055, "reason": "Mean reversion time exit for BTC (3662 candles elapsed)"}, {"timestamp": "2025-11-10 17:00:00", "asset": "ETH", "price": 3554.33, "size": 0.5356190188803557, "pnl": 14.065355435797985, "pnl_pct": 0.7443162975791173, "reason": "Trend-exit (50%) triggered for ETH"}, {"timestamp": "2025-11-10 18:00:00", "asset": "ETH", "price": 3531.33, "size": 0.5356190188803557, "pnl": 1.746118001549803, "pnl_pct": 0.0924017947489641, "reason": "Mean reversion time exit for ETH (3385 candles elapsed)"}, {"timestamp": "2025-11-11 19:00:00", "asset": "ETH", "price": 3455.22, "size": 1.0648342834737758, "pnl": -93.98227385939572, "pnl_pct": -2.490771783670298, "reason": "Trailing stop-loss triggered for ETH (price $3,455.22 < stop $3,466.30, HWM=$3,573.51, ATR stop=3.0%)"}, {"timestamp": "2025-11-11 23:00:00", "asset": "BTC", "price": 103009.35, "size": 0.0357998715163478, "pnl": -96.95178004571198, "pnl_pct": -2.561694841280304, "reason": "Mean reversion time exit for BTC (3356 candles elapsed)"}, {"timestamp": "2025-11-29 17:00:00", "asset": "ETH", "price": 2970.9, "size": 1.2266898059244542, "pnl": -76.65584597221869, "pnl_pct": -2.060071405259456, "reason": "Trailing stop-loss triggered for ETH (price $2,970.90 < stop $2,982.37, HWM=$3,074.61, ATR stop=3.0%)"}, {"timestamp": "2025-12-01 00:00:00", "asset": "BTC", "price": 87002.03, "size": 0.0407155669605088, "pnl": -161.39528596444825, "pnl_pct": -4.357639117912193, "reason": "Trailing stop-loss triggered for BTC (price $87,002.03 < stop $89,596.81, HWM=$92,367.85, ATR stop=3.0%)"}, {"timestamp": "2025-12-01 00:00:00", "asset": "ETH", "price": 2836.83, "size": 1.2415616151698667, "pnl": -166.45616574582436, "pnl_pct": -4.512773906896905, "reason": "Trailing stop-loss triggered for ETH (price $2,836.83 < stop $2,958.65, HWM=$3,050.15, ATR stop=3.0%)"}, {"timestamp": "2025-12-01 06:00:00", "asset": "ETH", "price": 2824.73, "size": 0.6320774992683763, "pnl": -7.648137741147366, "pnl_pct": -0.4265324323276309, "reason": "Trend-exit (50%) triggered for ETH"}, {"timestamp": "2025-12-01 08:00:00", "asset": "BTC", "price": 86857.98, "size": 0.0206098226932119, "pnl": -2.9688449589571064, "pnl_pct": -0.1655708493238594, "reason": "Trend-exit (50%) triggered for BTC"}, {"timestamp": "2025-12-01 11:00:00", "asset": "BTC", "price": 86119.98, "size": 0.0206098226932119, "pnl": -18.17889410654766, "pnl_pct": -1.013826918751215, "reason": "Mean reversion time exit for BTC (2888 candles elapsed)"}, {"timestamp": "2025-12-01 11:00:00", "asset": "ETH", "price": 2837.41, "size": 0.6320774992683763, "pnl": 0.3666049495755032, "pnl_pct": 0.0204453562603346, "reason": "Mean reversion time exit for ETH (2888 candles elapsed)"}, {"timestamp": "2025-12-04 19:00:00", "asset": "ETH", "price": 3119.99, "size": 1.158370984589331, "pnl": 43.84434176670629, "pnl_pct": 1.2280428533421484, "reason": "Trailing stop-loss triggered for ETH (price $3,119.99 < stop $3,124.65, HWM=$3,222.34, ATR stop=3.0%)"}, {"timestamp": "2025-12-05 13:00:00", "asset": "BTC", "price": 90491.88, "size": 0.0382683734111043, "pnl": -113.73934603381348, "pnl_pct": -3.179993415648774, "reason": "Trailing stop-loss triggered for BTC (price $90,491.88 < stop $91,131.53, HWM=$93,950.03, ATR stop=3.0%)"}, {"timestamp": "2025-12-05 16:00:00", "asset": "ETH", "price": 3033.25, "size": 1.1451005907331506, "pnl": -99.3260252401933, "pnl_pct": -2.7801371158240773, "reason": "Trailing stop-loss triggered for ETH (price $3,033.25 < stop $3,084.08, HWM=$3,184.28, ATR stop=3.1%)"}, {"timestamp": "2025-12-06 00:00:00", "asset": "BTC", "price": 89428.2, "size": 0.0391831548072484, "pnl": -41.67833810537422, "pnl_pct": -1.175442481690081, "reason": "Mean reversion time exit for BTC (2779 candles elapsed)"}, {"timestamp": "2025-12-06 00:00:00", "asset": "ETH", "price": 3026.41, "size": 1.1534605129118571, "pnl": -7.889669908317501, "pnl_pct": -0.2255007005687037, "reason": "Mean reversion time exit for ETH (2779 candles elapsed)"}, {"timestamp": "2025-12-11 01:00:00", "asset": "ETH", "price": 3255.85, "size": 1.1255012612462192, "pnl": 160.67656005550998, "pnl_pct": 4.585797391016633, "reason": "Trailing stop-loss triggered for ETH (price $3,255.85 < stop $3,259.53, HWM=$3,390.93, ATR stop=3.9%)"}, {"timestamp": "2025-12-11 02:00:00", "asset": "BTC", "price": 90099.99, "size": 0.038484768424412, "pnl": -116.85784477767449, "pnl_pct": -3.2602377200078303, "reason": "Trailing stop-loss triggered for BTC (price $90,099.99 < stop $90,342.37, HWM=$93,136.46, ATR stop=3.0%)"}, {"timestamp": "2025-12-11 07:00:00", "asset": "ETH", "price": 3202.13, "size": 1.082992002247267, "pnl": -58.178330360723066, "pnl_pct": -1.6499531612328533, "reason": "Mean reversion time exit for ETH (2652 candles elapsed)"}, {"timestamp": "2025-12-11 07:00:00", "asset": "BTC", "price": 90291.84, "size": 0.0388747008335167, "pnl": 7.458111354910216, "pnl_pct": 0.2129301013240825, "reason": "Mean reversion time exit for BTC (2652 candles elapsed)"}, {"timestamp": "2025-12-11 13:00:00", "asset": "BTC", "price": 90099.94, "size": 0.0387964275915022, "pnl": -5.930421921636935, "pnl_pct": -0.1693687065664417, "reason": "Mean reversion time exit for BTC (2646 candles elapsed)"}, {"timestamp": "2025-12-11 21:00:00", "asset": "BTC", "price": 92882.74, "size": 0.0390867760150373, "pnl": 130.97744121982942, "pnl_pct": 3.742737217390912, "reason": "Mean reversion target reached for BTC (price $92,882.74 >= SMA $90,398.32)"}, {"timestamp": "2025-12-12 15:00:00", "asset": "BTC", "price": 89951.05, "size": 0.0383263357644436, "pnl": -95.67441523213802, "pnl_pct": -2.7002501748021768, "reason": "Mean reversion time exit for BTC (2620 candles elapsed)"}, {"timestamp": "2025-12-12 15:00:00", "asset": "ETH", "price": 3071.2, "size": 1.0961553044513597, "pnl": -176.6563888653818, "pnl_pct": -4.985830786174816, "reason": "Mean reversion time exit for ETH (2620 candles elapsed)"}, {"timestamp": "2025-12-12 16:00:00", "asset": "ETH", "price": 3069.78, "size": 1.1241181379256395, "pnl": -1.596247755854165, "pnl_pct": -0.046235998958044, "reason": "Mean reversion time exit for ETH (2619 candles elapsed)"}, {"timestamp": "2025-12-12 16:00:00", "asset": "BTC", "price": 90069.26, "size": 0.0383807818274186, "pnl": 4.536992219818785, "pnl_pct": 0.131415920103195, "reason": "Mean reversion time exit for BTC (2619 candles elapsed)"}, {"timestamp": "2025-12-12 17:00:00", "asset": "ETH", "price": 3066.4, "size": 1.1249574475538566, "pnl": -3.802356172731834, "pnl_pct": -0.1101056101740272, "reason": "Mean reversion time exit for ETH (2618 candles elapsed)"}, {"timestamp": "2025-12-12 17:00:00", "asset": "BTC", "price": 90111.66, "size": 0.038341292837888, "pnl": 1.625670816326874, "pnl_pct": 0.0470748843723223, "reason": "Mean reversion time exit for BTC (2618 candles elapsed)"}, {"timestamp": "2025-12-12 18:00:00", "asset": "ETH", "price": 3079.78, "size": 1.1259608373227272, "pnl": 15.065356003377929, "pnl_pct": 0.436342290633962, "reason": "Mean reversion time exit for ETH (2617 candles elapsed)"}, {"timestamp": "2025-12-12 18:00:00", "asset": "BTC", "price": 90396.06, "size": 0.0383152004032154, "pnl": 10.896842994673989, "pnl_pct": 0.3156084351348065, "reason": "Mean reversion time exit for BTC (2617 candles elapsed)"}, {"timestamp": "2025-12-23 06:00:00", "asset": "BTC", "price": 87342.07, "size": 0.0385116240592435, "pnl": -97.61541350296466, "pnl_pct": -2.8201948067337, "reason": "Trailing stop-loss triggered for BTC (price $87,342.07 < stop $87,397.09, HWM=$90,100.09, ATR stop=3.0%)"}, {"timestamp": "2025-12-23 06:00:00", "asset": "ETH", "price": 2957.79, "size": 1.1316333029076948, "pnl": -117.03351618671375, "pnl_pct": -3.3784026577725834, "reason": "Trailing stop-loss triggered for ETH (price $2,957.79 < stop $2,969.37, HWM=$3,061.21, ATR stop=3.0%)"}, {"timestamp": "2025-12-23 10:00:00", "asset": "ETH", "price": 2965.6, "size": 1.1460417185362048, "pnl": 8.950585821767618, "pnl_pct": 0.2640484956673683, "reason": "Mean reversion time exit for ETH (2361 candles elapsed)"}, {"timestamp": "2025-12-23 15:00:00", "asset": "ETH", "price": 2927.1, "size": 1.1636966342682704, "pnl": 13.522154890197273, "pnl_pct": 0.3985621578608045, "reason": "Mean reversion time exit for ETH (2356 candles elapsed)"}, {"timestamp": "2025-12-23 15:00:00", "asset": "BTC", "price": 87390.51, "size": 0.0390804879589317, "pnl": 22.52951050344427, "pnl_pct": 0.6640517280503744, "reason": "Mean reversion time exit for BTC (2356 candles elapsed)"}, {"timestamp": "2025-12-29 12:00:00", "asset": "BTC", "price": 87266.44, "size": 0.0386886036084765, "pnl": -28.534779591431743, "pnl_pct": -0.8380870003735108, "reason": "Mean reversion time exit for BTC (2215 candles elapsed)"}, {"timestamp": "2025-12-31 22:00:00", "asset": "BTC", "price": 87591.31, "size": 0.0382898760812566, "pnl": -41.37948618225346, "pnl_pct": -1.2187500000000018, "reason": "Mean reversion time exit for BTC (2157 candles elapsed)"}, {"timestamp": "2025-12-31 22:00:00", "asset": "ETH", "price": 2972.29, "size": 1.137929380258469, "pnl": -12.983774228748644, "pnl_pct": -0.3824111003116859, "reason": "Mean reversion time exit for ETH (2157 candles elapsed)"}, {"timestamp": "2026-01-01 00:00:00", "asset": "ETH", "price": 2974.28, "size": 1.1382881466723942, "pnl": 8.4688638112425, "pnl_pct": 0.2507718650146318, "reason": "Mean reversion time exit for ETH (2155 candles elapsed)"}, {"timestamp": "2026-01-02 04:00:00", "asset": "ETH", "price": 3007.75, "size": 1.127229655214285, "pnl": 10.48323579349335, "pnl_pct": 0.3101602494622213, "reason": "Mean reversion target reached for ETH (price $3,007.75 >= SMA $2,990.49)"}, {"timestamp": "2026-01-06 17:00:00", "asset": "BTC", "price": 91527.98, "size": 0.038059155827992, "pnl": 94.08147202367944, "pnl_pct": 2.775759072942874, "reason": "Trailing stop-loss triggered for BTC (price $91,527.98 < stop $91,613.21, HWM=$94,446.61, ATR stop=3.0%)"}, {"timestamp": "2026-01-07 14:00:00", "asset": "ETH", "price": 3188.8, "size": 1.1231174263606254, "pnl": 197.9606775703237, "pnl_pct": 5.850876668857508, "reason": "Trailing stop-loss triggered for ETH (price $3,188.80 < stop $3,196.72, HWM=$3,295.59, ATR stop=3.0%)"}, {"timestamp": "2026-01-07 18:00:00", "asset": "BTC", "price": 90810.04, "size": 0.0380552442985551, "pnl": -27.32138209170444, "pnl_pct": -0.7843940180915165, "reason": "Trailing stop-loss triggered for BTC (price $90,810.04 < stop $90,910.35, HWM=$93,722.01, ATR stop=3.0%)"}, {"timestamp": "2026-01-08 12:00:00", "asset": "ETH", "price": 3091.77, "size": 1.0930407042800598, "pnl": -106.05773953629432, "pnl_pct": -3.042837431008538, "reason": "Trailing stop-loss triggered for ETH (price $3,091.77 < stop $3,093.14, HWM=$3,188.80, ATR stop=3.0%)"}, {"timestamp": "2026-01-09 12:00:00", "asset": "BTC", "price": 90341.23, "size": 0.0380468179618175, "pnl": -17.836728728679645, "pnl_pct": -0.5162534891516413, "reason": "Mean reversion time exit for BTC (1951 candles elapsed)"}, {"timestamp": "2026-01-09 12:00:00", "asset": "ETH", "price": 3081.15, "size": 1.1075442257078614, "pnl": -11.76211967701738, "pnl_pct": -0.3434925625127372, "reason": "Mean reversion time exit for ETH (1951 candles elapsed)"}, {"timestamp": "2026-01-13 09:00:00", "asset": "BTC", "price": 92186.3, "size": 0.0372096769249495, "pnl": 3.76487511126652, "pnl_pct": 0.1098766011273122, "reason": "Mean reversion target reached for BTC (price $92,186.30 >= SMA $91,508.44)"}, {"timestamp": "2026-01-16 15:00:00", "asset": "BTC", "price": 94531.87, "size": 0.0360020330373205, "pnl": -24.373016345935863, "pnl_pct": -0.7110577734047108, "reason": "Trailing stop-loss triggered for BTC (price $94,531.87 < stop $94,745.73, HWM=$97,676.01, ATR stop=3.0%)"}, {"timestamp": "2026-01-16 15:00:00", "asset": "ETH", "price": 3262.92, "size": 1.02982534199687, "pnl": -65.78524284676041, "pnl_pct": -1.9201635205001844, "reason": "Trailing stop-loss triggered for ETH (price $3,262.92 < stop $3,282.79, HWM=$3,384.32, ATR stop=3.0%)"}, {"timestamp": "2026-01-19 00:00:00", "asset": "ETH", "price": 3210.87, "size": 1.0412942303523829, "pnl": -54.19936468984133, "pnl_pct": -1.5951969401640342, "reason": "Trailing stop-loss triggered for ETH (price $3,210.87 < stop $3,260.07, HWM=$3,360.90, ATR stop=3.0%)"}, {"timestamp": "2026-01-19 00:00:00", "asset": "BTC", "price": 92668.25, "size": 0.0359419502660996, "pnl": -66.98213735490845, "pnl_pct": -1.971419797365692, "reason": "Trailing stop-loss triggered for BTC (price $92,668.25 < stop $92,674.92, HWM=$95,541.15, ATR stop=3.0%)"}, {"timestamp": "2026-01-19 13:00:00", "asset": "BTC", "price": 92975.03, "size": 0.0362288695004651, "pnl": 11.114292585352814, "pnl_pct": 0.3310518974945609, "reason": "Mean reversion time exit for BTC (1710 candles elapsed)"}, {"timestamp": "2026-01-19 13:00:00", "asset": "ETH", "price": 3215.98, "size": 1.045593853406236, "pnl": 5.342984590905871, "pnl_pct": 0.1591468978812571, "reason": "Mean reversion time exit for ETH (1710 candles elapsed)"}, {"timestamp": "2026-01-29 03:00:00", "asset": "ETH", "price": 2948.07, "size": 1.138040954612142, "pnl": -7.727298081816571, "pnl_pct": -0.2297909207204407, "reason": "Mean reversion time exit for ETH (1480 candles elapsed)"}, {"timestamp": "2026-01-29 03:00:00", "asset": "BTC", "price": 87906.07, "size": 0.0383170922249327, "pnl": 5.55329617615962, "pnl_pct": 0.1651414281993224, "reason": "Mean reversion time exit for BTC (1480 candles elapsed)"}, {"timestamp": "2026-01-29 04:00:00", "asset": "ETH", "price": 2954.7, "size": 1.1404162817854893, "pnl": 7.560959948237269, "pnl_pct": 0.2248928960302709, "reason": "Mean reversion time exit for ETH (1479 candles elapsed)"}, {"timestamp": "2026-01-29 04:00:00", "asset": "BTC", "price": 88170.06, "size": 0.0382456755016274, "pnl": 10.096475875674514, "pnl_pct": 0.3003091822896708, "reason": "Mean reversion time exit for BTC (1479 candles elapsed)"}, {"timestamp": "2026-02-26 16:00:00", "asset": "ETH", "price": 1984.0, "size": 1.6399963185729771, "pnl": -114.16014373586496, "pnl_pct": -3.3896406815315583, "reason": "Trailing stop-loss triggered for ETH (price $1,984.00 < stop $2,010.52, HWM=$2,075.31, ATR stop=3.1%)"}, {"timestamp": "2026-02-27 10:00:00", "asset": "ETH", "price": 1981.01, "size": 1.667845696455997, "pnl": -4.986858632403255, "pnl_pct": -0.1507056451612864, "reason": "Trailing stop-loss triggered for ETH (price $1,981.01 < stop $1,983.92, HWM=$2,045.28, ATR stop=3.0%)"}, {"timestamp": "2026-02-27 14:00:00", "asset": "BTC", "price": 65899.36, "size": 0.0496920421550935, "pnl": -99.41638413758756, "pnl_pct": -2.9464649563379908, "reason": "Trailing stop-loss triggered for BTC (price $65,899.36 < stop $65,902.78, HWM=$67,941.01, ATR stop=3.0%)"}, {"timestamp": "2026-02-27 21:00:00", "asset": "ETH", "price": 1921.15, "size": 1.6692917213379443, "pnl": -99.92380243928892, "pnl_pct": -3.021690955623646, "reason": "Mean reversion time exit for ETH (766 candles elapsed)"}, {"timestamp": "2026-02-27 21:00:00", "asset": "BTC", "price": 65529.54, "size": 0.0496797531426827, "pnl": -18.37256630722686, "pnl_pct": -0.5611890616236681, "reason": "Mean reversion time exit for BTC (766 candles elapsed)"}, {"timestamp": "2026-03-03 08:00:00", "asset": "ETH", "price": 1952.59, "size": 1.6042309326404494, "pnl": -123.22097793611329, "pnl_pct": -3.784862520942156, "reason": "Trailing stop-loss triggered for ETH (price $1,952.59 < stop $1,990.37, HWM=$2,054.00, ATR stop=3.1%)"}, {"timestamp": "2026-03-03 08:00:00", "asset": "BTC", "price": 66992.02, "size": 0.0471428808433321, "pnl": -100.69672205254848, "pnl_pct": -3.0899052352295286, "reason": "Trailing stop-loss triggered for BTC (price $66,992.02 < stop $67,367.67, HWM=$69,451.21, ATR stop=3.0%)"}, {"timestamp": "2026-03-05 07:00:00", "asset": "ETH", "price": 2105.29, "size": 1.6291116011917373, "pnl": 248.76534150197813, "pnl_pct": 7.820382159081007, "reason": "Trailing stop-loss triggered for ETH (price $2,105.29 < stop $2,111.12, HWM=$2,179.02, ATR stop=3.1%)"}, {"timestamp": "2026-03-05 16:00:00", "asset": "BTC", "price": 71321.88, "size": 0.0474830736761031, "pnl": 205.5950613872119, "pnl_pct": 6.4632474136471885, "reason": "Trailing stop-loss triggered for BTC (price $71,321.88 < stop $71,522.86, HWM=$73,734.91, ATR stop=3.0%)"}, {"timestamp": "2026-03-05 17:00:00", "asset": "ETH", "price": 2059.48, "size": 1.588512031168577, "pnl": -72.76973614783265, "pnl_pct": -2.1759472566724725, "reason": "Trailing stop-loss triggered for ETH (price $2,059.48 < stop $2,075.01, HWM=$2,156.88, ATR stop=3.8%)"}, {"timestamp": "2026-03-06 13:00:00", "asset": "ETH", "price": 2020.29, "size": 1.601653519059277, "pnl": -62.76880141193351, "pnl_pct": -1.9029075300561304, "reason": "Trailing stop-loss triggered for ETH (price $2,020.29 < stop $2,029.33, HWM=$2,092.09, ATR stop=3.0%)"}, {"timestamp": "2026-03-06 14:00:00", "asset": "BTC", "price": 68397.59, "size": 0.0465408038187495, "pnl": -136.09880719913144, "pnl_pct": -4.100130282600523, "reason": "Trailing stop-loss triggered for BTC (price $68,397.59 < stop $69,182.22, HWM=$71,321.88, ATR stop=3.0%)"}, {"timestamp": "2026-03-07 19:00:00", "asset": "ETH", "price": 1955.12, "size": 1.6110358768008537, "pnl": -104.99120809111172, "pnl_pct": -3.225774517519764, "reason": "Trailing stop-loss triggered for ETH (price $1,955.12 < stop $1,959.68, HWM=$2,020.29, ATR stop=3.0%)"}, {"timestamp": "2026-03-07 21:00:00", "asset": "BTC", "price": 67451.74, "size": 0.0470936309908772, "pnl": -44.54351087272062, "pnl_pct": -1.3828703613679827, "reason": "Mean reversion time exit for BTC (574 candles elapsed)"}, {"timestamp": "2026-03-08 03:00:00", "asset": "ETH", "price": 1947.37, "size": 1.6435480936751814, "pnl": 8.546450087110316, "pnl_pct": 0.2677417527816805, "reason": "Mean reversion time exit for ETH (568 candles elapsed)"}, {"timestamp": "2026-03-08 05:00:00", "asset": "BTC", "price": 67145.98, "size": 0.0239745444376003, "pnl": 12.344972421809189, "pnl_pct": 0.7727927486070207, "reason": "Trend-exit (50%) triggered for BTC"}, {"timestamp": "2026-03-08 05:00:00", "asset": "ETH", "price": 1948.94, "size": 0.8242006980231017, "pnl": 8.868399510728523, "pnl_pct": 0.5551599954596531, "reason": "Trend-exit (50%) triggered for ETH"}, {"timestamp": "2026-03-08 12:00:00", "asset": "BTC", "price": 67315.43, "size": 0.0239745444376003, "pnl": 16.40745897676038, "pnl_pct": 1.0271035760199387, "reason": "Mean reversion time exit for BTC (559 candles elapsed)"}, {"timestamp": "2026-03-08 12:00:00", "asset": "ETH", "price": 1946.15, "size": 0.8242006980231017, "pnl": 6.5688795632440815, "pnl_pct": 0.4112105170830382, "reason": "Mean reversion time exit for ETH (559 candles elapsed)"}, {"timestamp": "2026-03-11 05:00:00", "asset": "ETH", "price": 2015.6, "size": 1.5515945669920128, "pnl": -82.23451205057654, "pnl_pct": -2.5621193077443705, "reason": "Trailing stop-loss triggered for ETH (price $2,015.60 < stop $2,018.81, HWM=$2,081.25, ATR stop=3.0%)"}, {"timestamp": "2026-03-11 11:00:00", "asset": "BTC", "price": 69179.97, "size": 0.0451627873713563, "pnl": -85.26824581286837, "pnl_pct": -2.656639086035784, "reason": "Trailing stop-loss triggered for BTC (price $69,179.97 < stop $69,336.80, HWM=$71,481.24, ATR stop=3.0%)"}, {"timestamp": "2026-03-12 22:00:00", "asset": "ETH", "price": 2065.6, "size": 1.5671426966945758, "pnl": 78.35713483472864, "pnl_pct": 2.480650922802141, "reason": "Mean reversion target reached for ETH (price $2,065.60 >= SMA $2,053.66)"}, {"timestamp": "2026-03-12 22:00:00", "asset": "BTC", "price": 70178.55, "size": 0.0456006409562294, "pnl": 45.535888046071705, "pnl_pct": 1.4434524906558943, "reason": "Mean reversion target reached for BTC (price $70,178.55 >= SMA $70,014.56)"}, {"timestamp": "2026-03-13 17:00:00", "asset": "ETH", "price": 2102.62, "size": 1.5079154756060416, "pnl": -24.518705633354784, "pnl_pct": -0.7673865438344918, "reason": "Trailing stop-loss triggered for ETH (price $2,102.62 < stop $2,108.22, HWM=$2,186.50, ATR stop=3.6%)"}, {"timestamp": "2026-03-13 17:00:00", "asset": "BTC", "price": 71043.02, "size": 0.044742149700434, "pnl": -16.474506941196523, "pnl_pct": -0.5156191820249956, "reason": "Trailing stop-loss triggered for BTC (price $71,043.02 < stop $71,212.20, HWM=$73,414.64, ATR stop=3.0%)"}, {"timestamp": "2026-03-18 11:00:00", "asset": "ETH", "price": 2269.8, "size": 1.5130777500264492, "pnl": 252.9563382494221, "pnl_pct": 7.951032521330537, "reason": "Trailing stop-loss triggered for ETH (price $2,269.80 < stop $2,290.45, HWM=$2,361.29, ATR stop=3.0%)"}, {"timestamp": "2026-03-18 11:00:00", "asset": "BTC", "price": 72962.74, "size": 0.0447817046454473, "pnl": 85.96833404195831, "pnl_pct": 2.7021936848968364, "reason": "Trailing stop-loss triggered for BTC (price $72,962.74 < stop $73,358.41, HWM=$75,627.23, ATR stop=3.0%)"}, {"timestamp": "2026-03-18 14:00:00", "asset": "ETH", "price": 2190.8, "size": 1.4514064805376714, "pnl": -114.66111196247584, "pnl_pct": -3.48048286192616, "reason": "Trailing stop-loss triggered for ETH (price $2,190.80 < stop $2,201.71, HWM=$2,269.80, ATR stop=3.0%)"}, {"timestamp": "2026-03-19 06:00:00", "asset": "BTC", "price": 70587.88, "size": 0.045151846401662, "pnl": -107.2293139454514, "pnl_pct": -3.2548942103873824, "reason": "Trailing stop-loss triggered for BTC (price $70,587.88 < stop $70,773.86, HWM=$72,962.74, ATR stop=3.0%)"}, {"timestamp": "2026-03-19 10:00:00", "asset": "ETH", "price": 2172.89, "size": 1.4741866554746423, "pnl": -26.402682999551416, "pnl_pct": -0.8175095855395442, "reason": "Mean reversion time exit for ETH (297 candles elapsed)"}, {"timestamp": "2026-03-19 10:00:00", "asset": "BTC", "price": 70129.69, "size": 0.0455515508887503, "pnl": -20.871265101716745, "pnl_pct": -0.649105767165703, "reason": "Mean reversion time exit for BTC (297 candles elapsed)"}, {"timestamp": "2026-03-19 13:00:00", "asset": "BTC", "price": 69900.0, "size": 0.0462491986261154, "pnl": 28.138012444128435, "pnl_pct": 0.8780285056197101, "reason": "Mean reversion time exit for BTC (294 candles elapsed)"}, {"timestamp": "2026-03-20 20:00:00", "asset": "ETH", "price": 2133.13, "size": 0.7576078307465898, "pnl": 9.04583749911444, "pnl_pct": 0.5628915844408056, "reason": "Trend-exit (50%) triggered for ETH"}, {"timestamp": "2026-03-21 23:00:00", "asset": "ETH", "price": 2084.64, "size": 0.7576078307465898, "pnl": -27.69056621378786, "pnl_pct": -1.723089397932298, "reason": "Trailing stop-loss triggered for ETH (price $2,084.64 < stop $2,098.95, HWM=$2,163.87, ATR stop=3.0%)"}, {"timestamp": "2026-03-26 15:00:00", "asset": "BTC", "price": 69035.84, "size": 0.0450084878963166, "pnl": -100.64663037910668, "pnl_pct": -3.137514993613899, "reason": "Trailing stop-loss triggered for BTC (price $69,035.84 < stop $69,133.85, HWM=$71,272.01, ATR stop=3.0%)"}]